baai_flagdataset_ks3util/__init__.py
baai_flagdataset_ks3util/baai_helper/__init__.py
baai_flagdataset_ks3util/baai_helper/baai_print.py
baai_flagdataset_ks3util/baai_prepare.py
baai_flagdataset_ks3util/cmd/cmd_run.py
baai_flagdataset_ks3util/share_cp.py
baai_flagdataset_ks3util/share_url.py
baai_flagdataset_ks3util-0.1.9.dist-info/METADATA
baai_flagdataset_ks3util-0.1.9.dist-info/WHEEL
baai_flagdataset_ks3util-0.1.9.dist-info/entry_points.txt
baai_flagdataset_ks3util-0.1.9.dist-info/RECORD
