Metadata-Version: 2.3
Name: baai-flagdataset-ks3util
Version: 0.1.9
Summary: baai-flagdataset-ks3util
Author: 史红光
Author-email: hgshi@baai.ac.cn
Requires-Python: >=3.10
Classifier: Programming Language :: Python :: 3
Classifier: Programming Language :: Python :: 3.10
Classifier: Programming Language :: Python :: 3.11
Classifier: Programming Language :: Python :: 3.12
Classifier: Programming Language :: Python :: 3.13
Requires-Dist: colorama (>=0.4.6,<0.5.0)
